{
    "4": 742,
    "6": 672,
    "5": 610,
    "2": 567,
    "7": 514,
    "8": 332,
    "3": 326,
    "9": 296,
    "12": 260,
    "11": 247,
    "10": 241,
    "13": 200,
    "14": 188,
    "38": 180,
    "44": 161,
    "43": 159,
    "62": 152,
    "37": 148,
    "42": 148,
    "15": 146,
    "41": 143,
    "16": 143,
    "50": 143,
    "36": 143,
    "39": 141,
    "35": 140,
    "52": 140,
    "59": 139,
    "40": 139,
    "48": 138,
    "54": 136,
    "1": 135,
    "46": 135,
    "47": 134,
    "34": 132,
    "32": 130,
    "53": 127,
    "33": 126,
    "31": 125,
    "55": 124,
    "63": 123,
    "45": 123,
    "61": 123,
    "65": 123,
    "58": 122,
    "56": 120,
    "17": 119,
    "49": 118,
    "57": 117,
    "64": 117,
    "51": 116,
    "18": 116,
    "60": 115,
    "71": 104,
    "76": 104,
    "70": 103,
    "66": 103,
    "69": 103,
    "21": 102,
    "30": 99,
    "73": 99,
    "29": 99,
    "28": 98,
    "19": 98,
    "82": 97,
    "27": 96,
    "75": 95,
    "77": 95,
    "79": 94,
    "25": 93,
    "89": 92,
    "74": 92,
    "84": 91,
    "87": 91,
    "23": 88,
    "67": 88,
    "26": 87,
    "20": 87,
    "72": 85,
    "85": 85,
    "22": 84,
    "78": 83,
    "24": 82,
    "88": 79,
    "81": 79,
    "80": 79,
    "68": 79,
    "96": 75,
    "83": 73,
    "86": 72,
    "90": 68,
    "92": 67,
    "99": 64,
    "97": 64,
    "93": 64,
    "103": 62,
    "91": 60,
    "94": 59,
    "98": 58,
    "111": 58,
    "104": 56,
    "108": 55,
    "106": 55,
    "95": 54,
    "107": 51,
    "100": 51,
    "102": 51,
    "101": 48,
    "124": 47,
    "119": 47,
    "105": 42,
    "123": 41,
    "109": 41,
    "113": 40,
    "110": 39,
    "128": 39,
    "118": 38,
    "114": 38,
    "120": 38,
    "116": 38,
    "126": 38,
    "112": 37,
    "127": 35,
    "122": 35,
    "130": 34,
    "125": 32,
    "149": 32,
    "115": 31,
    "138": 31,
    "143": 30,
    "146": 29,
    "140": 29,
    "134": 29,
    "117": 28,
    "136": 28,
    "148": 27,
    "135": 27,
    "172": 26,
    "129": 26,
    "141": 26,
    "121": 26,
    "133": 25,
    "154": 25,
    "131": 24,
    "150": 24,
    "144": 24,
    "142": 23,
    "165": 22,
    "139": 22,
    "158": 21,
    "132": 20,
    "173": 20,
    "137": 20,
    "163": 20,
    "153": 20,
    "155": 20,
    "157": 19,
    "160": 19,
    "151": 19,
    "167": 19,
    "156": 19,
    "161": 19,
    "147": 18,
    "145": 18,
    "171": 17,
    "179": 17,
    "183": 17,
    "194": 17,
    "174": 17,
    "152": 15,
    "166": 15,
    "164": 14,
    "159": 14,
    "169": 14,
    "168": 14,
    "187": 13,
    "182": 13,
    "178": 13,
    "176": 13,
    "175": 12,
    "206": 12,
    "184": 12,
    "185": 12,
    "177": 12,
    "198": 12,
    "162": 11,
    "207": 11,
    "202": 11,
    "180": 11,
    "186": 11,
    "199": 11,
    "196": 11,
    "218": 11,
    "195": 11,
    "170": 10,
    "191": 10,
    "211": 10,
    "201": 10,
    "181": 10,
    "209": 10,
    "192": 9,
    "188": 9,
    "208": 9,
    "229": 8,
    "214": 8,
    "232": 8,
    "224": 8,
    "189": 8,
    "219": 8,
    "215": 8,
    "204": 8,
    "212": 8,
    "226": 8,
    "231": 8,
    "268": 7,
    "240": 7,
    "205": 7,
    "223": 7,
    "241": 7,
    "233": 6,
    "193": 6,
    "237": 6,
    "216": 6,
    "250": 6,
    "190": 6,
    "197": 6,
    "271": 6,
    "203": 6,
    "228": 6,
    "260": 6,
    "210": 5,
    "251": 5,
    "254": 5,
    "309": 5,
    "236": 5,
    "242": 5,
    "234": 5,
    "213": 5,
    "310": 5,
    "245": 5,
    "238": 5,
    "246": 5,
    "225": 5,
    "221": 5,
    "220": 4,
    "255": 4,
    "256": 4,
    "253": 4,
    "287": 4,
    "263": 4,
    "200": 4,
    "266": 4,
    "222": 4,
    "275": 4,
    "276": 3,
    "257": 3,
    "284": 3,
    "252": 3,
    "267": 3,
    "314": 3,
    "343": 3,
    "217": 3,
    "293": 3,
    "259": 3,
    "335": 3,
    "280": 3,
    "312": 3,
    "281": 3,
    "316": 3,
    "304": 3,
    "239": 3,
    "313": 3,
    "296": 3,
    "383": 3,
    "323": 3,
    "243": 3,
    "351": 2,
    "334": 2,
    "367": 2,
    "388": 2,
    "405": 2,
    "403": 2,
    "277": 2,
    "318": 2,
    "248": 2,
    "344": 2,
    "247": 2,
    "279": 2,
    "300": 2,
    "319": 2,
    "328": 2,
    "235": 2,
    "283": 2,
    "265": 2,
    "424": 2,
    "269": 2,
    "302": 2,
    "308": 2,
    "394": 2,
    "278": 2,
    "264": 2,
    "322": 2,
    "306": 2,
    "391": 2,
    "261": 2,
    "244": 2,
    "227": 2,
    "398": 1,
    "379": 1,
    "421": 1,
    "273": 1,
    "321": 1,
    "659": 1,
    "372": 1,
    "603": 1,
    "384": 1,
    "419": 1,
    "582": 1,
    "431": 1,
    "345": 1,
    "393": 1,
    "369": 1,
    "596": 1,
    "347": 1,
    "336": 1,
    "426": 1,
    "480": 1,
    "288": 1,
    "282": 1,
    "349": 1,
    "332": 1,
    "326": 1,
    "440": 1,
    "305": 1,
    "425": 1,
    "435": 1,
    "299": 1,
    "315": 1,
    "448": 1,
    "230": 1,
    "637": 1,
    "629": 1,
    "286": 1,
    "333": 1,
    "337": 1,
    "270": 1,
    "488": 1,
    "386": 1,
    "258": 1,
    "365": 1,
    "342": 1,
    "366": 1,
    "330": 1,
    "329": 1,
    "377": 1,
    "387": 1,
    "346": 1,
    "340": 1,
    "375": 1,
    "378": 1,
    "412": 1,
    "470": 1,
    "357": 1,
    "436": 1,
    "355": 1,
    "428": 1,
    "331": 1,
    "422": 1,
    "317": 1,
    "390": 1,
    "415": 1,
    "320": 1,
    "303": 1,
    "290": 1,
    "295": 1,
    "301": 1,
    "399": 1,
    "416": 1
}